{
  "name": "Adolescent School Dropout",
  "uuid": "54636d6b-33bf-4faf-9397-eb3b1d9b1792",
  "formType": "ProgramEncounter",
  "programName": "Adolescent",
  "userUUID": "5fed2907-df3a-4867-aef5-c87f4c78a31a",
  "encounterTypes": [
    "Dropout Home Visit"
  ],
  "formElementGroups": [
    {
      "uuid": "774323a1-4597-4de4-9e0d-e657537b5236",
      "name": "Dropping Out Details",
      "displayOrder": 1,
      "display": "Dropping Out Details",
      "formElements": [
        {
          "name": "When did you leave school",
          "uuid": "7dda44bc-4700-4f0b-b51e-6b76617a6ac8",
          "keyValues": [],
          "concept": {
            "uuid": "c41ff8c3-1f33-4512-a5cd-e9b01d92913f",
            "name": "When did you leave school"
          },
          "displayOrder": 1,
          "mandatory": true
        },
        {
          "name": "Dropped out of which standard",
          "uuid": "afebf488-96e8-48bc-a15d-75de5da97887",
          "keyValues": [],
          "type": "SingleSelect",
          "concept": {
            "uuid": "32005c85-c1de-4fc3-9314-6d6a10f34b57",
            "name": "Dropped out of which standard"
          },
          "displayOrder": 2,
          "mandatory": true
        },
        {
          "name": "Reason for dropping as per student / parent",
          "uuid": "e99598f5-3797-4636-9cb1-18157ef03671",
          "keyValues": [],
          "type": "MultiSelect",
          "concept": {
            "uuid": "c9aceef5-fb03-49ed-a455-bfa603dddb28",
            "name": "Reason for dropping as per student / parent"
          },
          "displayOrder": 3,
          "mandatory": true
        },
        {
          "name": "Other reason according to student/parent",
          "uuid": "711fb359-354d-4475-9e28-3a1c6d2fe0a9",
          "concept": {
            "uuid": "2a61f823-241b-4c09-be98-26cd1db49d7b",
            "name": "Other reason according to student/parent"
          },
          "mandatory": true,
          "displayOrder": 4
        },
        {
          "name": "Reason for dropping as per teacher",
          "uuid": "e05ad605-ed75-4f36-bd30-b10bcc5cd1d8",
          "keyValues": [],
          "type": "MultiSelect",
          "concept": {
            "uuid": "5972d90a-bc65-4801-8658-db746b146444",
            "name": "Reason for dropping as per teacher"
          },
          "displayOrder": 5,
          "mandatory": true
        },
        {
          "name": "Other reason according to teacher",
          "uuid": "db04ee46-86a2-4e8d-84af-f612eff15895",
          "concept": {
            "uuid": "0cf89f36-ce0d-4b2e-b978-d6988375cc2b",
            "name": "Other reason according to teacher"
          },
          "mandatory": true,
          "displayOrder": 6
        },
        {
          "name": "What he/she is doing now?",
          "uuid": "5c719e93-f361-4bce-a802-51befe82334c",
          "keyValues": [],
          "type": "SingleSelect",
          "mandatory": true,
          "concept": {
            "uuid": "fedc7739-ddd8-4627-86b0-4ecdc066601e"
          },
          "displayOrder": 7
        },
        {
          "name": "Other activity (please specify)",
          "uuid": "92f8be44-582a-4af8-8ba4-48327046ddf9",
          "concept": {
            "uuid": "3a3f2078-ea0c-4dc0-ae4f-0777b95e8248",
            "name": "Other activity"
          },
          "mandatory": true,
          "displayOrder": 8
        },
        {
          "name": "How is the economic condition of family",
          "uuid": "0af1bdd7-22e8-443a-81f2-550953090e57",
          "keyValues": [],
          "type": "SingleSelect",
          "concept": {
            "uuid": "b76236df-a70a-4157-92ea-68c24ad21f4c",
            "name": "How is the economic condition of family"
          },
          "displayOrder": 9,
          "mandatory": true
        },
        {
          "name": "Are you ready for re-admission to school",
          "uuid": "f02fec91-d196-4a8b-819e-8b81ecb58778",
          "keyValues": [],
          "type": "SingleSelect",
          "concept": {
            "uuid": "4c7d5f3e-8284-4207-8d7f-9ef7727eb811",
            "name": "Are you ready for re-admission to school"
          },
          "displayOrder": 10,
          "mandatory": true
        },
        {
          "name": "Name of school",
          "uuid": "f0fc75aa-e602-4b4d-ab44-b4a87e577ac0",
          "keyValues": [],
          "mandatory": true,
          "displayOrder": 11,
          "concept": {
            "uuid": "bdb1eb17-a803-40e3-947d-d812d5def18d",
            "name": "Name of school"
          }
        }
      ]
    },
    {
      "uuid": "5f794156-1087-4a64-81bd-4e8b223edaf9",
      "name": "Counselling for Dropout",
      "displayOrder": 2,
      "display": "Counselling for Dropout",
      "formElements": [
        {
          "name": "Counselling checklist for dropout",
          "uuid": "4a01e3c2-4ce7-46f5-9c23-e6533e7e8a10",
          "keyValues": [],
          "type": "SingleSelect",
          "concept": {
            "uuid": "efaa640c-f320-496f-b407-8351148da734",
            "name": "Counselling checklist for dropout"
          },
          "mandatory": false,
          "displayOrder": 1
        },
        {
          "name": "Counselling for dropout Done",
          "uuid": "68ec3c60-17f8-46a6-8d52-163f68d9aacd",
          "keyValues": [],
          "type": "SingleSelect",
          "concept": {
            "uuid": "17628553-31d6-46ff-b702-315c9d32a30f",
            "name": "Counselling for dropout Done"
          },
          "mandatory": true,
          "displayOrder": 2
        }
      ]
    }
  ]
}